{
  "$schema": "https://unpkg.com/knip@5/schema.json",
  "workspaces": {
    ".": {
      "entry": ["package.json", "test/**/*.ts"]
    },
    "packages/core": {
      "entry": ["test/**/*.ts"],
      "project": ["src/**/*.ts", "test/**/*.ts"]
    },
    "packages/vue": {
      "entry": ["test/**/*.ts"],
      "project": ["src/**/*.ts", "test/**/*.ts"],
      "ignoreDependencies": ["vue-tsc"]
    },
    "packages/recipes": {
      "entry": ["test/**/*.ts"],
      "project": ["src/**/*.{ts,vue}", "test/**/*.ts"],
      "ignoreDependencies": ["vue-tsc"]
    },
    "packages/nuxt": {
      "entry": ["src/runtime/*.ts"],
      "project": ["src/**/*.ts", "test/**/*.ts"],
      "ignoreDependencies": ["nuxt", "@nuxt-photo/recipes"],
      "ignoreUnresolved": ["#imports"]
    },
    "docs": {
      "entry": [
        "app/**/*.vue",
        "app/**/*.ts",
        "server/**/*.ts",
        "content.config.ts"
      ],
      "project": ["app/**/*.ts", "server/**/*.ts", "*.ts"],
      "ignoreDependencies": [
        "@iconify-json/lucide",
        "@iconify-json/simple-icons",
        "@iconify-json/vscode-icons",
        "@nuxt/fonts"
      ]
    },
    "playground": {
      "entry": ["pages/**/*.vue", "components/**/*.vue", "composables/**/*.ts"],
      "project": ["*.ts", "composables/**/*.ts"]
    },
    "playground-tailwind": {
      "entry": ["components/**/*.vue", "composables/**/*.ts"],
      "project": ["*.ts", "composables/**/*.ts"]
    }
  }
}
